nessus_report_parser/__init__.py
nessus_report_parser/model/__init__.py
nessus_report_parser/model/family_item.py
nessus_report_parser/model/family_selection.py
nessus_report_parser/model/helpers.py
nessus_report_parser/model/host_properties.py
nessus_report_parser/model/nessus_client_data_v2.py
nessus_report_parser/model/report.py
nessus_report_parser/model/report_host.py
nessus_report_parser/model/report_item.py
nessus_report_parser-0.2.8.2.dist-info/METADATA
nessus_report_parser-0.2.8.2.dist-info/RECORD
nessus_report_parser-0.2.8.2.dist-info/WHEEL
nessus_report_parser-0.2.8.2.dist-info/top_level.txt
tests/__init__.py
tests/test_family_item.py
tests/test_family_selection.py
tests/test_helpers.py
tests/test_host_properties.py
tests/test_nessus_parser.py
tests/test_report_item.py
