Metadata-Version: 2.1
Name: nessus-report-parser
Version: 0.2.8.2
Summary: A wrapper around the tapioca-nessus_report_parser for translating the Nessus API documents into Python Objects
Home-page: https://github.com/siteblindado/nessus_report_parser-report-nessus_report_parser
Author: Flávio Cardoso Ferreira Pontes
Author-email: flavio.pontes@siteblindado.com.br
License: MIT
Keywords: nessus
Platform: UNKNOWN
Classifier: Development Status :: 5 - Production/Stable
Classifier: Intended Audience :: Developers
Classifier: License :: OSI Approved :: MIT License
Classifier: Natural Language :: English
Classifier: Programming Language :: Python :: 3.4
Classifier: Programming Language :: Python :: 3.5
Classifier: Programming Language :: Python :: 3.6
Requires-Dist: tapioca-nessus
Requires-Dist: lxml (>=4.2.1)
